Workbook

Sheet 10cdr 10cpr
A2: CDR | B2: 0.1 | D2: CPR | E2: 0.1
A4: As of Date | B4: 42825 | C4: Coupon | D4: 0.0402 | E4: Orig Balance | F4: 10000000000 | G4: Payment Method | H4: Equal Payment | I4: Frequency | J4: Monthly | K4: Accrual Method | L4: 30/360 | M4: Term | N4: 1 year
A6: Asset Payment Date | B6: Begin Bal | C6: Loss | D6: Interest | E6: Principal | F6: Performing | G6: Days | H6: SUR_CDR | I6: SUR_CPR | J6: Scheduled Principal | K6: Scheduled Interest | L6: Prepay Principal | M6: Prepay Interest
A7: 42825 | B7: 10000000000 | C7: 0 | D7: 0 | E7: 0 | F7: 10000000000 | H7: 1 | I7: 1 | J7: 0 | K7: 0 | L7: 0
A8: 42855 | B8: =F7 -> 10000000000 | C8: =(I7+I8)*(H7-H8)/2*'0cpr 0cdr'!F7 -> 88688286 | D8: =M8+K8 -> 33054341 | E8: =J8+L8 -> 8.922677e+08 | F8: =B8-J8-L8-C8 -> 9.019044e+09 | G8: =A8-$B$4+1 -> 31 | H8: =(1-$B$2)^(G8/365) -> 0.99109149 | I8: =(1-$E$2)^(G8/365) -> 0.99109149 | J8: ='0cpr 0cdr'!E8*H8*I8 -> 8.0357942e+08 | K8: ='0cpr 0cdr'!D8*I8*H8 -> 32905788 | L8: =(I7-I8)*(H7+H8)/2*'0cpr 0cdr'!F7 -> 88688286 | M8: =L8*$D$4*30/360/2 -> 148552.88
A9: 42886 | B9: =F8 -> 9.019044e+09 | C9: =(I8+I9)*(H8-H9)/2*'0cpr 0cdr'!F8 -> 79988355 | D9: =M9+K9 -> 29811856 | E9: =J9+L9 -> 8.719584e+08 | F9: =B9-J9-L9-C9 -> 8.0670973e+09 | G9: =A9-$B$4+1 -> 62 | H9: =(1-$B$2)^(G9/365) -> 0.98226234 | I9: =(1-$E$2)^(G9/365) -> 0.98226234 | J9: ='0cpr 0cdr'!E9*H9*I9 -> 7.9197004e+08 | K9: ='0cpr 0cdr'!D9*I9*H9 -> 29677875 | L9: =(I8-I9)*(H8+H9)/2*'0cpr 0cdr'!F8 -> 79988355 | M9: =L9*$D$4*30/360/2 -> 133980.49
A10: 42916 | B10: =F9 -> 8.0670973e+09 | C10: =(I9+I10)*(H9-H10)/2*'0cpr 0cdr'!F9 -> 69257707 | D10: =M10+K10 -> 26676756 | E10: =J10+L10 -> 8.5023684e+08 | F10: =B10-J10-L10-C10 -> 7.1476027e+09 | G10: =A10-$B$4+1 -> 92 | H10: =(1-$B$2)^(G10/365) -> 0.9737929 | I10: =(1-$E$2)^(G10/365) -> 0.9737929 | J10: ='0cpr 0cdr'!E10*H10*I10 -> 7.8097913e+08 | K10: ='0cpr 0cdr'!D10*I10*H10 -> 26560749 | L10: =(I9-I10)*(H9+H10)/2*'0cpr 0cdr'!F9 -> 69257707 | M10: =L10*$D$4*30/360/2 -> 116006.66
A11: 42947 | B11: =F10 -> 7.1476027e+09 | C11: =(I10+I11)*(H10-H11)/2*'0cpr 0cdr'!F10 -> 63390863 | D11: =M11+K11 -> 23625930 | E11: =J11+L11 -> 8.3308713e+08 | F11: =B11-J11-L11-C11 -> 6.2511247e+09 | G11: =A11-$B$4+1 -> 123 | H11: =(1-$B$2)^(G11/365) -> 0.96511786 | I11: =(1-$E$2)^(G11/365) -> 0.96511786 | J11: ='0cpr 0cdr'!E11*H11*I11 -> 7.6969626e+08 | K11: ='0cpr 0cdr'!D11*I11*H11 -> 23519750 | L11: =(I10-I11)*(H10+H11)/2*'0cpr 0cdr'!F10 -> 63390863 | M11: =L11*$D$4*30/360/2 -> 106179.7
A12: 42978 | B12: =F11 -> 6.2511247e+09 | C12: =(I11+I12)*(H11-H12)/2*'0cpr 0cdr'!F11 -> 55440154 | D12: =M12+K12 -> 20662681 | E12: =J12+L12 -> 8.1401656e+08 | F12: =B12-J12-L12-C12 -> 5.381668e+09 | G12: =A12-$B$4+1 -> 154 | H12: =(1-$B$2)^(G12/365) -> 0.9565201 | I12: =(1-$E$2)^(G12/365) -> 0.9565201 | J12: ='0cpr 0cdr'!E12*H12*I12 -> 7.585764e+08 | K12: ='0cpr 0cdr'!D12*I12*H12 -> 20569819 | L12: =(I11-I12)*(H11+H12)/2*'0cpr 0cdr'!F11 -> 55440154 | M12: =L12*$D$4*30/360/2 -> 92862.257
A13: 43008 | B13: =F12 -> 5.381668e+09 | C13: =(I12+I13)*(H12-H13)/2*'0cpr 0cdr'!F12 -> 46202739 | D13: =M13+K13 -> 17796419 | E13: =J13+L13 -> 7.9425167e+08 | F13: =B13-J13-L13-C13 -> 4.5412136e+09 | G13: =A13-$B$4+1 -> 184 | H13: =(1-$B$2)^(G13/365) -> 0.94827262 | I13: =(1-$E$2)^(G13/365) -> 0.94827262 | J13: ='0cpr 0cdr'!E13*H13*I13 -> 7.4804893e+08 | K13: ='0cpr 0cdr'!D13*I13*H13 -> 17719030 | L13: =(I12-I13)*(H12+H13)/2*'0cpr 0cdr'!F12 -> 46202739 | M13: =L13*$D$4*30/360/2 -> 77389.587
A14: 43039 | B14: =F13 -> 4.5412136e+09 | C14: =(I13+I14)*(H13-H14)/2*'0cpr 0cdr'!F13 -> 40275245 | D14: =M14+K14 -> 15010682 | E14: =J14+L14 -> 7.7751705e+08 | F14: =B14-J14-L14-C14 -> 3.7234213e+09 | G14: =A14-$B$4+1 -> 215 | H14: =(1-$B$2)^(G14/365) -> 0.93982492 | I14: =(1-$E$2)^(G14/365) -> 0.93982492 | J14: ='0cpr 0cdr'!E14*H14*I14 -> 7.3724181e+08 | K14: ='0cpr 0cdr'!D14*I14*H14 -> 14943221 | L14: =(I13-I14)*(H13+H14)/2*'0cpr 0cdr'!F13 -> 40275245 | M14: =L14*$D$4*30/360/2 -> 67461.035
A15: 43069 | B15: =F14 -> 3.7234213e+09 | C15: =(I14+I15)*(H14-H15)/2*'0cpr 0cdr'!F14 -> 31966346 | D15: =M15+K15 -> 12312831 | E15: =J15+L15 -> 7.5897676e+08 | F15: =B15-J15-L15-C15 -> 2.9324782e+09 | G15: =A15-$B$4+1 -> 245 | H15: =(1-$B$2)^(G15/365) -> 0.93172139 | I15: =(1-$E$2)^(G15/365) -> 0.93172139 | J15: ='0cpr 0cdr'!E15*H15*I15 -> 7.2701041e+08 | K15: ='0cpr 0cdr'!D15*I15*H15 -> 12259287 | L15: =(I14-I15)*(H14+H15)/2*'0cpr 0cdr'!F14 -> 31966346 | M15: =L15*$D$4*30/360/2 -> 53543.63
A16: 43100 | B16: =F15 -> 2.9324782e+09 | C16: =(I15+I16)*(H15-H16)/2*'0cpr 0cdr'!F15 -> 26007647 | D16: =M16+K16 -> 9693113.6 | E16: =J16+L16 -> 7.4251488e+08 | F16: =B16-J16-L16-C16 -> 2.1639557e+09 | G16: =A16-$B$4+1 -> 276 | H16: =(1-$B$2)^(G16/365) -> 0.92342115 | I16: =(1-$E$2)^(G16/365) -> 0.92342115 | J16: ='0cpr 0cdr'!E16*H16*I16 -> 7.1650723e+08 | K16: ='0cpr 0cdr'!D16*I16*H16 -> 9649550.8 | L16: =(I15-I16)*(H15+H16)/2*'0cpr 0cdr'!F15 -> 26007647 | M16: =L16*$D$4*30/360/2 -> 43562.808
A17: 43131 | B17: =F16 -> 2.1639557e+09 | C17: =(I16+I17)*(H16-H17)/2*'0cpr 0cdr'!F16 -> 19191752 | D17: =M17+K17 -> 7152813 | E17: =J17+L17 -> 7.2534755e+08 | F17: =B17-J17-L17-C17 -> 1.4194164e+09 | G17: =A17-$B$4+1 -> 307 | H17: =(1-$B$2)^(G17/365) -> 0.91519484 | I17: =(1-$E$2)^(G17/365) -> 0.91519484 | J17: ='0cpr 0cdr'!E17*H17*I17 -> 7.061558e+08 | K17: ='0cpr 0cdr'!D17*I17*H17 -> 7120666.8 | L17: =(I16-I17)*(H16+H17)/2*'0cpr 0cdr'!F16 -> 19191752 | M17: =L17*$D$4*30/360/2 -> 32146.185
A18: 43159 | B18: =F17 -> 1.4194164e+09 | C18: =(I17+I18)*(H17-H18)/2*'0cpr 0cdr'!F17 -> 11380136 | D18: =M18+K18 -> 4385939.8 | E18: =J18+L18 -> 7.0885237e+08 | F18: =B18-J18-L18-C18 -> 6.9918388e+08 | G18: =A18-$B$4+1 -> 335 | H18: =(1-$B$2)^(G18/365) -> 0.90782764 | I18: =(1-$E$2)^(G18/365) -> 0.90782764 | J18: ='0cpr 0cdr'!E18*H18*I18 -> 6.9747223e+08 | K18: ='0cpr 0cdr'!D18*I18*H18 -> 4366878.1 | L18: =(I17-I18)*(H17+H18)/2*'0cpr 0cdr'!F17 -> 11380136 | M18: =L18*$D$4*30/360/2 -> 19061.727
A19: 43190 | B19: =F18 -> 6.9918388e+08 | C19: =(I18+I19)*(H18-H19)/2*'0cpr 0cdr'!F18 -> 6200942 | D19: =M19+K19 -> 2541178.2 | E19: =J19+L19 -> 6.9298294e+08 | F19: =B19-J19-L19-C19 -> -0.0085216612 | G19: =A19-$B$4+1 -> 366 | H19: =(1-$B$2)^(G19/365) -> 0.89974024 | I19: =(1-$E$2)^(G19/365) -> 0.89974024 | J19: ='0cpr 0cdr'!E19*H19*I19 -> 6.86782e+08 | K19: ='0cpr 0cdr'!D19*I19*H19 -> 2530791.7 | L19: =(I18-I19)*(H18+H19)/2*'0cpr 0cdr'!F18 -> 6200942 | M19: =L19*$D$4*30/360/2 -> 10386.578
F23: ='0cpr 0cdr'!F8*I8 -> 9.1001124e+09
F24: ='0cpr 0cdr'!F9*I9 -> 8.2127726e+09
F25: ='0cpr 0cdr'!F10*I10 -> 7.3399618e+09
F26: ='0cpr 0cdr'!F11*I11 -> 6.4770584e+09
F27: ='0cpr 0cdr'!F12*I12 -> 5.6262989e+09
F28: ='0cpr 0cdr'!F13*I13 -> 4.7889326e+09
F29: ='0cpr 0cdr'!F14*I14 -> 3.9618244e+09
F30: ='0cpr 0cdr'!F15*I15 -> 3.1473767e+09
F31: ='0cpr 0cdr'!F16*I16 -> 2.3434115e+09
F32: ='0cpr 0cdr'!F17*I17 -> 1.5509445e+09
F33: ='0cpr 0cdr'!F18*I18 -> 7.701725e+08
F34: ='0cpr 0cdr'!F19*I19 -> 0

Sheet 0cpr 0cdr
A2: CDR | B2: 0 | D2: CPR | E2: 0.1
A4: As of Date | B4: 42825 | C4: Coupon | D4: 0.0402 | E4: Orig Balance | F4: 10000000000 | G4: Payment Method | H4: Equal Payment | I4: Frequency | J4: Monthly | K4: Accrual Method | L4: 30/360 | M4: Term | N4: 1 year
A6: PaymentDate | B6: Begin Bal | C6: Loss | D6: Interest | E6: Principal | F6: Performing
A7: 42825 | B7: 10000000000 | C7: 0 | D7: 0 | E7: 0 | F7: 10000000000
A8: 42855 | B8: =F7 -> 10000000000 | C8: 0 | D8: 33500000 | E8: 8.1809042e+08 | F8: 9.1819096e+09
A9: 42886 | B9: =F8 -> 9.1819096e+09 | C9: 0 | D9: 30759397 | E9: 8.2083103e+08 | F9: 8.3610786e+09
A10: 42916 | B10: =F9 -> 8.3610786e+09 | C10: 0 | D10: 28009613 | E10: 8.2358081e+08 | F10: 7.5374977e+09
A11: 42947 | B11: =F10 -> 7.5374977e+09 | C11: 0 | D11: 25250617 | E11: 8.2633981e+08 | F11: 6.7111579e+09
A12: 42978 | B12: =F11 -> 6.7111579e+09 | C12: 0 | D12: 22482379 | E12: 8.2910804e+08 | F12: 5.8820499e+09
A13: 43008 | B13: =F12 -> 5.8820499e+09 | C13: 0 | D13: 19704867 | E13: 8.3188556e+08 | F13: 5.0501643e+09
A14: 43039 | B14: =F13 -> 5.0501643e+09 | C14: 0 | D14: 16918051 | E14: 8.3467237e+08 | F14: 4.215492e+09
A15: 43069 | B15: =F14 -> 4.215492e+09 | C15: 0 | D15: 14121898 | E15: 8.3746852e+08 | F15: 3.3780234e+09
A16: 43100 | B16: =F15 -> 3.3780234e+09 | C16: 0 | D16: 11316379 | E16: 8.4027404e+08 | F16: 2.5377494e+09
A17: 43131 | B17: =F16 -> 2.5377494e+09 | C17: 0 | D17: 8501460.5 | E17: 8.4308896e+08 | F17: 1.6946604e+09
A18: 43159 | B18: =F17 -> 1.6946604e+09 | C18: 0 | D18: 5298638.3 | E18: 8.4629178e+08 | F18: 8.4836865e+08
A19: 43190 | B19: =F18 -> 8.4836865e+08 | C19: 0 | D19: 3126238.5 | E19: 8.4836865e+08 | F19: 0
